dobbi/__init__.py
dobbi/job.py
dobbi/collections/__init__.py
dobbi/collections/chat_shortages.py
dobbi/collections/contractions.py
dobbi/collections/emoji.py
dobbi/collections/emoticons.py
dobbi-0.13.dist-info/LICENSE
dobbi-0.13.dist-info/METADATA
dobbi-0.13.dist-info/WHEEL
dobbi-0.13.dist-info/top_level.txt
dobbi-0.13.dist-info/RECORD
