Metadata-Version: 2.1
Name: dobbi
Version: 0.13
Summary: An open-source NLP library: fast text cleaning and preprocessing.
Home-page: https://github.com/iaramer/dobbi
Author: Iaroslav Amerkhanov
Author-email: amerkhanov.y@gmail.com
License: Apache License 2.0
Download-URL: https://github.com/iaramer/dobbi/archive/refs/tags/v0_13.tar.gz
Keywords: nlp,text,string,regexp,preprocess,clean
Platform: UNKNOWN
Classifier: Development Status :: 3 - Alpha
Classifier: Intended Audience :: Developers
Classifier: Topic :: Software Development :: Build Tools
Classifier: License :: OSI Approved :: Apache Software License
Classifier: Programming Language :: Python :: 3
Classifier: Programming Language :: Python :: 3.6
Classifier: Programming Language :: Python :: 3.7
Classifier: Programming Language :: Python :: 3.8
Classifier: Programming Language :: Python :: 3.9
Classifier: Programming Language :: Python :: 3.10
License-File: LICENSE
